AUTHORS
INSTALL
LICENSE
MANIFEST.in
README
setup.py
AnyMetaAPI.egg-info/PKG-INFO
AnyMetaAPI.egg-info/SOURCES.txt
AnyMetaAPI.egg-info/dependency_links.txt
AnyMetaAPI.egg-info/entry_points.txt
AnyMetaAPI.egg-info/requires.txt
AnyMetaAPI.egg-info/top_level.txt
anymeta/__init__.py
anymeta/manhole.py
anymeta/queue.py
anymeta/api/__init__.py
anymeta/api/base.py
anymeta/api/cli.py
anymeta/api/discovery.py
anymeta/api/registry.py
anymeta/api/oauth/__init__.py
anymeta/api/oauth/oauth.py
anymeta/api/oauth/example/client.py
anymeta/api/oauth/example/server.py
anymeta/availability/__init__.py
anymeta/availability/base.py
anymeta/availability/component.py
anymeta/availability/gui.py
anymeta/availability/test/__init__.py
anymeta/availability/test/test_component.py
anymeta/availability/test/test_service.py
anymeta/gtk/__init__.py
anymeta/gtk/autocomplete.py
anymeta/gtk/registry.glade
anymeta/gtk/registry.py
anymeta/test/__init__.py
anymeta/test/test_queue.py
bin/any-registry
bin/any-sms
bin/any-sms-status
debian/changelog
debian/compat
debian/control
debian/copyright
debian/docs
debian/python-anymeta.bash-completion
debian/rules
doc/CHANGELOG.txt
doc/api-examples/example-basic.py
doc/api-examples/example-registry.py
doc/api-examples/example-twisted.py
doc/gtk-examples/autocomplete.py
doc/gtk-examples/availability.py
doc/gtk-examples/registry.py
twisted/plugins/dropin.cache