Metadata-Version: 1.0
Name: AnyMetaAPI
Version: 1.27
Summary: Support library for accessing AnyMeta-based websites from Python.
Home-page: http://trac.mediamatic.nl/python-anymeta
Author: Arjan Scherpenisse
Author-email: arjan@mediamatic.nl
License: MIT
Keywords: anymeta mediamatic api web2.0 social network oauth
Platform: any
Classifier: Development Status :: 3 - Alpha
Classifier: Intended Audience :: Developers
Classifier: License :: OSI Approved :: MIT License
Classifier: Programming Language :: Python
Classifier: Topic :: Software Development :: Libraries :: Python Modules
